transpara/__init__.py
transpara/logging_config.py
transpara/tlogging.py
transpara/tracing.py
transpara/internal/output_tstore.py
transpara/internal/settings.py
transpara/internal/tauth_manager.py
transpara/internal/utils.py
transpara/internal/extra-hooks/hook-opentelemetry.py
transpara_sdk-0.47.0.dist-info/licenses/LICENSE.txt
transpara_sdk-0.47.0.dist-info/METADATA
transpara_sdk-0.47.0.dist-info/WHEEL
transpara_sdk-0.47.0.dist-info/top_level.txt
transpara_sdk-0.47.0.dist-info/RECORD
