Metadata-Version: 2.4
Name: transpara-sdk
Version: 0.47.0
Summary: Transpara Python SDK
Project-URL: homepage, https://transpara.com
License-File: LICENSE.txt
Requires-Dist: jsonpickle>=1.4.2
Requires-Dist: asyncio>=3.4.3
Requires-Dist: opentelemetry-api==1.20.0
Requires-Dist: opentelemetry-sdk==1.20.0
Requires-Dist: opentelemetry-exporter-otlp==1.20.0
Requires-Dist: opentelemetry-exporter-otlp-proto-http==1.20.0
Requires-Dist: pydantic>=2.7.0
Requires-Dist: requests>=2.26.0
Requires-Dist: pytest-dotenv>=0.5.2
Requires-Dist: httpx>=0.25.1
Requires-Dist: tenacity>=8.2.2
Requires-Dist: asyncio>=3.4.3
Requires-Dist: pendulum>=2.1.2
Requires-Dist: pytz>=2022.6
Requires-Dist: pydantic-settings>=2.0.3
Requires-Dist: python-keycloak==5.5.1
Dynamic: license-file
